sysco-0.1.1b1.dist-info/METADATA
sysco-0.1.1b1.dist-info/WHEEL
sysco-0.1.1b1.dist-info/licenses/LICENSE
sysco/__init__.py
sysco/_core.abi3.so
sysco/_core.pyi
sysco/controller/__init__.py
sysco/controller/base_controller.py
sysco/py.typed
sysco-0.1.1b1.dist-info/RECORD
