Metadata-Version: 2.4
Name: sysco
Version: 0.1.1b1
Classifier: Development Status :: 3 - Alpha
Requires-Dist: cvxpy>=1.6.5
Requires-Dist: loguru>=0.7.3
Requires-Dist: numpy>=2.2.6
License-File: LICENSE
Summary: Library for system and control tools
Keywords: science,engineering,systems,controls,controller,discrete-time,model-based,data-driven
Author-email: Silvan Stadelmann <silvasta3@gmail.com>
License: Apache License 2.0
Requires-Python: >=3.13
Project-URL: Repository, https://github.com/silvasta/sysco
